source_paypal_transaction/__init__.py
source_paypal_transaction/components.py
source_paypal_transaction/manifest.yaml
source_paypal_transaction/run.py
source_paypal_transaction/source.py
source_paypal_transaction/spec.yaml
airbyte_source_paypal_transaction-2.5.8.dist-info/METADATA
airbyte_source_paypal_transaction-2.5.8.dist-info/WHEEL
airbyte_source_paypal_transaction-2.5.8.dist-info/entry_points.txt
airbyte_source_paypal_transaction-2.5.8.dist-info/RECORD
